{"hash":"9bfa97e5f71d3e2459f2681c879c3b1778226211","data":{"posts":{"totalCount":290,"pageInfo":{"totalPages":49,"currentPage":25,"isFirst":false,"isLast":false},"edges":[{"node":{"title":"Weird Dream","path":"/content/journal/weird-dream/"}},{"node":{"title":"新造敬老院","path":"/content/journal/nursing-home/"}},{"node":{"title":"China Hotel","path":"/content/journal/china-hotel/"}},{"node":{"title":"Today's a Great Day","path":"/content/journal/todays-a-great-day/"}},{"node":{"title":"This Week","path":"/content/journal/this-week/"}},{"node":{"title":"校园网真废","path":"/content/journal/crap-school-network/"}}]}},"context":{}}