{"hash":"9bfa97e5f71d3e2459f2681c879c3b1778226211","data":{"posts":{"totalCount":290,"pageInfo":{"totalPages":49,"currentPage":39,"isFirst":false,"isLast":false},"edges":[{"node":{"title":"没号了","path":"/content/journal/run-out-of-numbers/"}},{"node":{"title":"Ear Piercing","path":"/content/journal/ear-piercing/"}},{"node":{"title":"电耳镜检查","path":"/content/journal/ear-exam/"}},{"node":{"title":"学农总结","path":"/content/journal/summary-village-experience/"}},{"node":{"title":"复古舞?","path":"/content/journal/retro-dance/"}},{"node":{"title":"I'm Back!","path":"/content/journal/im-back/"}}]}},"context":{}}